devon_agent/.DS_Store
devon_agent/__main__.py
devon_agent/__version__.py
devon_agent/agent.py
devon_agent/agents/conversational_agent.py
devon_agent/agents/prompts/anthropic_prompts.py
devon_agent/agents/prompts/codegemma_prompts.py
devon_agent/agents/prompts/llama3_prompts.py
devon_agent/agents/prompts/openai_prompts.py
devon_agent/agents/task_agent.py
devon_agent/config.py
devon_agent/data_models.py
devon_agent/environment.py
devon_agent/environments/docker_environment.py
devon_agent/environments/job_environment.py
devon_agent/environments/shell_environment.py
devon_agent/environments/swebenchenv.py
devon_agent/environments/user_environment.py
devon_agent/event.py
devon_agent/experimental/dspyloop.py
devon_agent/model.py
devon_agent/server.py
devon_agent/session.py
devon_agent/test/test_edit_tool.py
devon_agent/test/test_event_system.py
devon_agent/test/test_fixures.py
devon_agent/test/test_job_environment.py
devon_agent/test/test_local_shell_environment.py
devon_agent/test/test_parse_commands.py
devon_agent/test/test_server.py
devon_agent/test/testfiles/sample
devon_agent/tool.py
devon_agent/tools/__init__.py
devon_agent/tools/codeindex.py
devon_agent/tools/codenav.py
devon_agent/tools/editorblock.py
devon_agent/tools/editortools.py
devon_agent/tools/edittools.py
devon_agent/tools/filesearchtools.py
devon_agent/tools/filetools.py
devon_agent/tools/lifecycle.py
devon_agent/tools/retrieval/ast_extractor.py
devon_agent/tools/retrieval/ast_parser.py
devon_agent/tools/retrieval/code_index.py
devon_agent/tools/retrieval/codebase_graph.py
devon_agent/tools/retrieval/file_discovery.py
devon_agent/tools/retrieval/file_tree/file_tree_tool.py
devon_agent/tools/retrieval/file_tree/llm.py
devon_agent/tools/retrieval/file_tree/prompt.py
devon_agent/tools/retrieval/graph_visualization.py
devon_agent/tools/retrieval/main.py
devon_agent/tools/semantic_search/code_graph_manager.py
devon_agent/tools/semantic_search/graph_construction/core/base_parser.py
devon_agent-0.1.25.dist-info/LICENSE
devon_agent-0.1.25.dist-info/METADATA
devon_agent-0.1.25.dist-info/WHEEL
devon_agent-0.1.25.dist-info/entry_points.txt
devon_agent-0.1.25.dist-info/RECORD
