Metadata-Version: 2.1
Name: devon-agent
Version: 0.1.25
Summary: 
Author: killind-dev
Author-email: 61808204+killind-dev@users.noreply.github.com
Requires-Python: >=3.10,<4
Classifier: Programming Language :: Python :: 3
Classifier: Programming Language :: Python :: 3.10
Classifier: Programming Language :: Python :: 3.11
Classifier: Programming Language :: Python :: 3.12
Provides-Extra: experimental
Provides-Extra: swebench
Requires-Dist: aiosqlite (>=0.20.0,<0.21.0)
Requires-Dist: anthropic (>=0.20.0,<0.21.0)
Requires-Dist: astroid (>=3.1.0,<4.0.0)
Requires-Dist: click (>=8.1.7,<9.0.0)
Requires-Dist: code-nav-devon (>=0.1.1,<0.2.0)
Requires-Dist: datasets (>=2.14.6,<2.15.0) ; extra == "swebench"
Requires-Dist: docker (>=7.0.0,<8.0.0)
Requires-Dist: dspy-ai (>=2.4.9,<3.0.0) ; extra == "experimental"
Requires-Dist: fastapi (>=0.110.3,<0.111.0)
Requires-Dist: ghapi (>=1.0.5,<2.0.0)
Requires-Dist: greenlet (>=3.0.3,<4.0.0)
Requires-Dist: gymnasium (>=0.29.1,<0.30.0) ; extra == "swebench"
Requires-Dist: litellm (>=1.37.9,<2.0.0)
Requires-Dist: llama-index (>=0.10.45,<0.11.0)
Requires-Dist: networkx (>=3.3,<4.0)
Requires-Dist: numpy (<=1.26.4)
Requires-Dist: openai (>=1.14.1,<2.0.0)
Requires-Dist: posthog (>=3.5.0,<4.0.0)
Requires-Dist: psutil (>=6.0.0,<7.0.0)
Requires-Dist: pydantic (>=2.5.0,<3.0.0)
Requires-Dist: pylint (>=3.1.0,<4.0.0)
Requires-Dist: pytest (>=8.1.1,<9.0.0)
Requires-Dist: pytest-json-report (>=1.5.0,<2.0.0)
Requires-Dist: python-dotenv (>=1.0.1,<2.0.0)
Requires-Dist: simple-parsing (>=0.1.5,<0.2.0)
Requires-Dist: sqlalchemy (>=2.0.30,<3.0.0)
Requires-Dist: swebench (==1.0.1) ; extra == "swebench"
Requires-Dist: tenacity (>=8.2.2,<9.0.0)
Requires-Dist: uvicorn (>=0.29.0,<0.30.0)
Requires-Dist: xmltodict (>=0.13.0,<0.14.0)
